{"Dico":[{"word":"CHAT","definition":"","node":[],"relation_sortant":[{"relation":"chat","type":"0","poids":"27"},{"relation":"Chat","type":"0","poids":"28"},{"relation":"chat>234460","type":"0","poids":"31"},{"relation":"clavardeur","type":"0","poids":"42"},{"relation":"_COM","type":"0","poids":"1000000"},{"relation":"_POL-NEUTRE_PC","type":"36","poids":"21"},{"relation":"_INFO-POLYSEMIC","type":"36","poids":"25"},{"relation":"_INFO-WIKI-YES","type":"36","poids":"31"},{"relation":"_INFO-CNRTL-NO","type":"36","poids":"50"},{"relation":"_POL-POS_PC","type":"36","poids":"79"},{"relation":"_POL-NEUTRE","type":"36","poids":"87"},{"relation":"_POL-POS","type":"36","poids":"323"},{"relation":"Chat","type":"777","poids":"10"},{"relation":"Carl von Linné","type":"777","poids":"10"},{"relation":"mammifère","type":"777","poids":"10"},{"relation":"Carnivora","type":"777","poids":"10"},{"relation":"carnivore","type":"777","poids":"10"},{"relation":"félidés","type":"777","poids":"10"},{"relation":"animaux de compagnie","type":"777","poids":"10"},{"relation":"races","type":"777","poids":"10"},{"relation":"Chien","type":"777","poids":"10"},{"relation":"chien","type":"777","poids":"10"},{"relation":"Furet","type":"777","poids":"10"},{"relation":"furet","type":"777","poids":"10"},{"relation":"Territoire","type":"777","poids":"10"},{"relation":"territorial","type":"777","poids":"10"},{"relation":"prédateur","type":"777","poids":"10"},{"relation":"rongeurs","type":"777","poids":"10"},{"relation":"Oiseau","type":"777","poids":"10"},{"relation":"oiseaux","type":"777","poids":"10"},{"relation":"phéromones","type":"777","poids":"10"},{"relation":"sous-espèce","type":"777","poids":"10"},{"relation":"Felis silvestris","type":"777","poids":"10"},{"relation":"chat sauvage","type":"777","poids":"10"},{"relation":"Néolithique","type":"777","poids":"10"},{"relation":"néolithique","type":"777","poids":"10"},{"relation":"Europe","type":"777","poids":"10"},{"relation":"Littérature","type":"777","poids":"10"},{"relation":"littérature","type":"777","poids":"10"},{"relation":"Peinture","type":"777","poids":"10"},{"relation":"peinture","type":"777","poids":"10"},{"relation":"Musique","type":"777","poids":"10"},{"relation":"musique","type":"777","poids":"10"},{"relation":"Wiktionnaire","type":"777","poids":"10"},{"relation":"Littré","type":"777","poids":"10"},{"relation":"langues afro-asiatiques","type":"777","poids":"10"},{"relation":"berbère","type":"777","poids":"10"},{"relation":"nubien","type":"777","poids":"10"},{"relation":"gallo-roman","type":"777","poids":"10"},{"relation":"écureuil","type":"777","poids":"10"},{"relation":"castré","type":"777","poids":"10"},{"relation":"mot-valise","type":"777","poids":"10"},{"relation":"argot","type":"777","poids":"10"},{"relation":"mâchoire supérieure","type":"777","poids":"10"},{"relation":"mâchoire inférieure","type":"777","poids":"10"},{"relation":"Felidae","type":"777","poids":"10"},{"relation":"clavicule","type":"777","poids":"10"},{"relation":"sternum","type":"777","poids":"10"},{"relation":"ligament","type":"777","poids":"10"},{"relation":"souplesse","type":"777","poids":"10"},{"relation":"épaules","type":"777","poids":"10"},{"relation":"carnivores","type":"777","poids":"10"},{"relation":"prémolaire","type":"777","poids":"10"},{"relation":"molaire","type":"777","poids":"10"},{"relation":"rugir","type":"777","poids":"10"},{"relation":"griffes","type":"777","poids":"10"},{"relation":"pouce","type":"777","poids":"10"},{"relation":"polydactylie","type":"777","poids":"10"},{"relation":"course","type":"777","poids":"10"},{"relation":"Australie","type":"777","poids":"10"},{"relation":"australien","type":"777","poids":"10"},{"relation":"tour de taille","type":"777","poids":"10"},{"relation":"nerf","type":"777","poids":"10"},{"relation":"estomac","type":"777","poids":"10"},{"relation":"intestin grêle","type":"777","poids":"10"},{"relation":"gros intestin","type":"777","poids":"10"},{"relation":"poils","type":"777","poids":"10"},{"relation":"robe","type":"777","poids":"10"},{"relation":"isolation","type":"777","poids":"10"},{"relation":"sphynx","type":"777","poids":"10"},{"relation":"pigmentation","type":"777","poids":"10"},{"relation":"fourrure","type":"777","poids":"10"},{"relation":"Génétique","type":"777","poids":"10"},{"relation":"écaille de tortue","type":"777","poids":"10"},{"relation":"crépusculaire","type":"777","poids":"10"},{"relation":"légendes","type":"777","poids":"10"},{"relation":"Tremblement de terre","type":"777","poids":"10"},{"relation":"tremblements de terre","type":"777","poids":"10"},{"relation":"Homo sapiens","type":"777","poids":"10"},{"relation":"humains","type":"777","poids":"10"},{"relation":"ultrasons","type":"777","poids":"10"},{"relation":"oreille","type":"777","poids":"10"},{"relation":"muscles","type":"777","poids":"10"},{"relation":"bruit","type":"777","poids":"10"},{"relation":"surdité","type":"777","poids":"10"},{"relation":"gène","type":"777","poids":"10"},{"relation":"allèle","type":"777","poids":"10"},{"relation":"oreille interne","type":"777","poids":"10"},{"relation":"vue","type":"777","poids":"10"},{"relation":"vision binoculaire","type":"777","poids":"10"},{"relation":"Homme","type":"777","poids":"10"},{"relation":"homme","type":"777","poids":"10"},{"relation":"pupille","type":"777","poids":"10"},{"relation":"rétine","type":"777","poids":"10"},{"relation":"paupières","type":"777","poids":"10"},{"relation":"nez","type":"777","poids":"10"},{"relation":"odorat","type":"777","poids":"10"},{"relation":"papilles","type":"777","poids":"10"},{"relation":"toucher","type":"777","poids":"10"},{"relation":"pression","type":"777","poids":"10"},{"relation":"organe de Jacobson","type":"777","poids":"10"},{"relation":"Cheval","type":"777","poids":"10"},{"relation":"cheval","type":"777","poids":"10"},{"relation":"organe voméro-nasal","type":"777","poids":"10"},{"relation":"babines","type":"777","poids":"10"},{"relation":"incisives","type":"777","poids":"10"},{"relation":"organe vestibulaire","type":"777","poids":"10"},{"relation":"écureuil volant","type":"777","poids":"10"},{"relation":"Noir","type":"777","poids":"10"},{"relation":"noir","type":"777","poids":"10"},{"relation":"race","type":"777","poids":"10"},{"relation":"Espèce","type":"777","poids":"10"},{"relation":"espèce","type":"777","poids":"10"},{"relation":"pedigree","type":"777","poids":"10"},{"relation":"CFA","type":"777","poids":"10"},{"relation":"rural","type":"777","poids":"10"},{"relation":"Ville","type":"777","poids":"10"},{"relation":"urbain","type":"777","poids":"10"},{"relation":"appariement","type":"777","poids":"10"},{"relation":"polygyne","type":"777","poids":"10"},{"relation":"salive","type":"777","poids":"10"},{"relation":"selles","type":"777","poids":"10"},{"relation":"urine","type":"777","poids":"10"}],"Raffinement":[],"Raffinement_Morpho":[],"taille":0,"otherDef":""}]}